{"week1": {"jie1": {"name": "大学英语2", "theacher": "林晓曼 ", "week": "1-16", "jie": "1-2", "class": "18音乐表演1班 18音乐表演2班 18美术学1班"}, "jie2": {"name": "大学英语2", "theacher": "李冬燕 ", "week": "1-16", "jie": "3-4", "class": "18市场营销1班 18市场营销2班"}, "jie3": {"name": "数据库系统概论", "theacher": "索剑 ", "week": "1-12", "jie": "5-6", "class": "17软件工程1班 17软件工程2班"}, "jie4": {"name": "计算机组成原理", "theacher": "麦山 ", "week": "1-5, 7-9, 11, 13, 15", "jie": "7-8", "class": "17软件工程1班 17软件工程2班"}, "jie5": {"name": "形势与政策4", "theacher": "林清明 ", "week": "3-5", "jie": "9-11", "class": "17中文1班 17中文2班 17日语1班 17日语2班"}, "jie6": {"name": "", "theacher": "", "week": "", "jie": "", "class": ""}}, "week2": {"jie1": {"name": "大学英语2", "theacher": "林晓曼 ", "week": "1-16", "jie": "1-2", "class": "18音乐表演1班 18音乐表演2班 18美术学1班"}, "jie2": {"name": "大学英语2", "theacher": "林晓曼 ", "week": "1-16", "jie": "3-4", "class": "18表演1班 18体育教育3班 18社会体育1班"}, "jie3": {"name": "大学英语2", "theacher": "李巧丽 ", "week": "1-16", "jie": "5-6", "class": "18思想政治教育1班 18思想政治教育2班"}, "jie4": {"name": "大学英语2", "theacher": "李巧丽 ", "week": "1-16", "jie": "7-8", "class": "18土木工程1班 18土木工程2班"}, "jie5": {"name": "思想道德修养与法律基础", "theacher": "刘华1 ", "week": "1-16", "jie": "9-11", "class": "18软件工程1班 18软件工程2班"}, "jie6": {"name": "", "theacher": "", "week": "", "jie": "", "class": ""}}, "week3": {"jie1": {"name": "大学英语2", "theacher": "王小宁 ", "week": "1-16 单", "jie": "1-2", "class": "18电信工程1班 18电信工程2班"}, "jie2": {"name": "大学英语2", "theacher": "王小宁 ", "week": "1-16 单", "jie": "3-4", "class": "18审计学1班 18审计学2班"}, "jie3": {"name": "", "theacher": "", "week": "", "jie": "", "class": ""}, "jie4": {"name": "", "theacher": "", "week": "", "jie": "", "class": ""}, "jie5": {"name": "", "theacher": "", "week": "", "jie": "", "class": ""}, "jie6": {"name": "", "theacher": "", "week": "", "jie": "", "class": ""}}, "week4": {"jie1": {"name": "大学英语2", "theacher": "李冬燕 ", "week": "1-16 单", "jie": "1-2", "class": "18国际贸易1班 18国际贸易2班"}, "jie2": {"name": "大学英语2", "theacher": "李冬燕 ", "week": "1-16 单", "jie": "3-4", "class": "18市场营销1班 18市场营销2班"}, "jie3": {"name": "实用翻译", "theacher": "丁刚 ", "week": "1-16", "jie": "5-6", "class": "17市场营销1班 17市场营销2班 17财务管理2班"}, "jie4": {"name": "实用翻译", "theacher": "丁刚 ", "week": "1-16", "jie": "7-8", "class": "17历史学1班 17社会工作1班 17数学1班"}, "jie5": {"name": "就业指导", "theacher": "杜建聪 ", "week": "16", "jie": "9", "class": "16审计学1班 16审计学2班 16审计学3班"}, "jie6": {"name": "", "theacher": "", "week": "", "jie": "", "class": ""}}, "week5": {"jie1": {"name": "", "theacher": "", "week": "", "jie": "", "class": ""}, "jie2": {"name": "大学英语2", "theacher": "李冬燕 ", "week": "1-16", "jie": "3-4", "class": "18国际贸易1班 18国际贸易2班"}, "jie3": {"name": "思想道德修养与法律基础", "theacher": "魏顺光 ", "week": "1-16", "jie": "5-7", "class": "18日语1班 18日语2班 18网络工程3班"}, "jie4": {"name": "", "theacher": "", "week": "", "jie": "", "class": ""}, "jie5": {"name": "就业指导", "theacher": "杜建聪 ", "week": "16", "jie": "9", "class": "16财务管理4班 16物流管理1班 16物流管理2班"}, "jie6": {"name": "", "theacher": "", "week": "", "jie": "", "class": ""}}, "week6": {"jie1": {"name": "", "theacher": "", "week": "", "jie": "", "class": ""}, "jie2": {"name": "", "theacher": "", "week": "", "jie": "", "class": ""}, "jie3": {"name": "", "theacher": "", "week": "", "jie": "", "class": ""}, "jie4": {"name": "", "theacher": "", "week": "", "jie": "", "class": ""}, "jie5": {"name": "", "theacher": "", "week": "", "jie": "", "class": ""}, "jie6": {"name": "", "theacher": "", "week": "", "jie": "", "class": ""}}, "week7": {"jie1": {"name": "", "theacher": "", "week": "", "jie": "", "class": ""}, "jie2": {"name": "", "theacher": "", "week": "", "jie": "", "class": ""}, "jie3": {"name": "", "theacher": "", "week": "", "jie": "", "class": ""}, "jie4": {"name": "", "theacher": "", "week": "", "jie": "", "class": ""}, "jie5": {"name": "", "theacher": "", "week": "", "jie": "", "class": ""}, "jie6": {"name": "", "theacher": "", "week": "", "jie": "", "class": ""}}}
