{"week1": {"jie1": {"name": "", "theacher": "", "week": "", "jie": "", "class": ""}, "jie2": {"name": "", "theacher": "", "week": "", "jie": "", "class": ""}, "jie3": {"name": "", "theacher": "", "week": "", "jie": "", "class": ""}, "jie4": {"name": "", "theacher": "", "week": "", "jie": "", "class": ""}, "jie5": {"name": "", "theacher": "", "week": "", "jie": "", "class": ""}, "jie6": {"name": "", "theacher": "", "week": "", "jie": "", "class": ""}}, "week2": {"jie1": {"name": "", "theacher": "", "week": "", "jie": "", "class": ""}, "jie2": {"name": "", "theacher": "", "week": "", "jie": "", "class": ""}, "jie3": {"name": "人体解剖生理学实验1", "theacher": "李红伟 ", "week": "3-10", "jie": "5-7", "class": "17生物科学3班"}, "jie4": {"name": "", "theacher": "", "week": "", "jie": "", "class": ""}, "jie5": {"name": "", "theacher": "", "week": "", "jie": "", "class": ""}, "jie6": {"name": "", "theacher": "", "week": "", "jie": "", "class": ""}}, "week3": {"jie1": {"name": "电子测量与虚拟仪器实验", "theacher": "王文辕 ", "week": "9-14", "jie": "1-2", "class": "16电信工程1班"}, "jie2": {"name": "", "theacher": "", "week": "", "jie": "", "class": ""}, "jie3": {"name": "", "theacher": "", "week": "", "jie": "", "class": ""}, "jie4": {"name": "", "theacher": "", "week": "", "jie": "", "class": ""}, "jie5": {"name": "", "theacher": "", "week": "", "jie": "", "class": ""}, "jie6": {"name": "", "theacher": "", "week": "", "jie": "", "class": ""}}, "week4": {"jie1": {"name": "", "theacher": "", "week": "", "jie": "", "class": ""}, "jie2": {"name": "", "theacher": "", "week": "", "jie": "", "class": ""}, "jie3": {"name": "人体解剖生理学实验1", "theacher": "李红伟 ", "week": "3-10", "jie": "5-7", "class": "17生物科学2班"}, "jie4": {"name": "", "theacher": "", "week": "", "jie": "", "class": ""}, "jie5": {"name": "", "theacher": "", "week": "", "jie": "", "class": ""}, "jie6": {"name": "", "theacher": "", "week": "", "jie": "", "class": ""}}, "week5": {"jie1": {"name": "", "theacher": "", "week": "", "jie": "", "class": ""}, "jie2": {"name": "", "theacher": "", "week": "", "jie": "", "class": ""}, "jie3": {"name": "人体解剖生理学实验1", "theacher": "李红伟 ", "week": "3-10", "jie": "5-7", "class": "17生物科学1班"}, "jie4": {"name": "", "theacher": "", "week": "", "jie": "", "class": ""}, "jie5": {"name": "", "theacher": "", "week": "", "jie": "", "class": ""}, "jie6": {"name": "", "theacher": "", "week": "", "jie": "", "class": ""}}, "week6": {"jie1": {"name": "", "theacher": "", "week": "", "jie": "", "class": ""}, "jie2": {"name": "", "theacher": "", "week": "", "jie": "", "class": ""}, "jie3": {"name": "", "theacher": "", "week": "", "jie": "", "class": ""}, "jie4": {"name": "", "theacher": "", "week": "", "jie": "", "class": ""}, "jie5": {"name": "", "theacher": "", "week": "", "jie": "", "class": ""}, "jie6": {"name": "", "theacher": "", "week": "", "jie": "", "class": ""}}, "week7": {"jie1": {"name": "", "theacher": "", "week": "", "jie": "", "class": ""}, "jie2": {"name": "", "theacher": "", "week": "", "jie": "", "class": ""}, "jie3": {"name": "", "theacher": "", "week": "", "jie": "", "class": ""}, "jie4": {"name": "", "theacher": "", "week": "", "jie": "", "class": ""}, "jie5": {"name": "", "theacher": "", "week": "", "jie": "", "class": ""}, "jie6": {"name": "", "theacher": "", "week": "", "jie": "", "class": ""}}}
